arrow_sdk.py
constants.py
utilities.py
arrow_markets_python_sdk-1.0.0.dist-info/METADATA
arrow_markets_python_sdk-1.0.0.dist-info/WHEEL
arrow_markets_python_sdk-1.0.0.dist-info/top_level.txt
arrow_markets_python_sdk-1.0.0.dist-info/RECORD
