Metadata-Version: 2.1
Name: arrow-markets-python-sdk
Version: 1.0.0
Summary: Arrow Markets SDK
Requires-Python: >=3.7
Requires-Dist: requests
Requires-Dist: web3
